material_ui/__init__.py
material_ui/_component.py
material_ui/_font_utils.py
material_ui/_lab.py
material_ui/_utils.py
material_ui/checkbox.py
material_ui/combobox.py
material_ui/elevation.py
material_ui/hook.py
material_ui/icon.py
material_ui/layout_basics.py
material_ui/menu.py
material_ui/py.typed
material_ui/ripple.py
material_ui/shape.py
material_ui/switch.py
material_ui/typography.py
material_ui/buttons/__init__.py
material_ui/buttons/_button_base.py
material_ui/buttons/elevated_button.py
material_ui/buttons/filled_button.py
material_ui/buttons/filled_tonal_button.py
material_ui/buttons/outlined_button.py
material_ui/buttons/text_button.py
material_ui/progress_indicators/__init__.py
material_ui/progress_indicators/_base_progress.py
material_ui/progress_indicators/circular_progress.py
material_ui/progress_indicators/linear_progress.py
material_ui/text_fields/__init__.py
material_ui/text_fields/_base_text_field.py
material_ui/text_fields/filled_text_field.py
material_ui/text_fields/outlined_text_field.py
material_ui/theming/__init__.py
material_ui/theming/dynamic_color.py
material_ui/theming/theme_hook.py
material_ui/tokens/__init__.py
material_ui/tokens/_token_converter.py
material_ui/tokens/_utils.py
material_ui/tokens/md_comp_assist_chip.py
material_ui/tokens/md_comp_badge.py
material_ui/tokens/md_comp_bottom_app_bar.py
material_ui/tokens/md_comp_carousel_item.py
material_ui/tokens/md_comp_checkbox.py
material_ui/tokens/md_comp_circular_progress_indicator.py
material_ui/tokens/md_comp_date_picker.py
material_ui/tokens/md_comp_dialog.py
material_ui/tokens/md_comp_divider.py
material_ui/tokens/md_comp_elevated_button.py
material_ui/tokens/md_comp_elevated_card.py
material_ui/tokens/md_comp_extended_fab.py
material_ui/tokens/md_comp_fab.py
material_ui/tokens/md_comp_filled_button.py
material_ui/tokens/md_comp_filled_card.py
material_ui/tokens/md_comp_filled_icon_button.py
material_ui/tokens/md_comp_filled_text_field.py
qt_material_ui-0.5.1.dist-info/METADATA
qt_material_ui-0.5.1.dist-info/WHEEL
qt_material_ui-0.5.1.dist-info/licenses/LICENSE
qt_material_ui-0.5.1.dist-info/RECORD
