Metadata-Version: 2.4
Name: qt-material-ui
Version: 0.5.1
Summary: Material 3 component library for Qt Widgets
Project-URL: Repository, https://github.com/herobank110/qt-material-ui
Project-URL: Documentation, https://qt-material-ui.readthedocs.io
License-Expression: MIT
License-File: LICENSE
Keywords: components,material,qt,ui,widgets
Classifier: Development Status :: 4 - Beta
Requires-Python: >=3.10
Requires-Dist: materialyoucolor==2.*
Requires-Dist: qtpy==2.4.*
Requires-Dist: typing-extensions==4.*
Provides-Extra: dev
Requires-Dist: httpx; extra == 'dev'
Requires-Dist: mypy; extra == 'dev'
Requires-Dist: pyautogui; extra == 'dev'
Requires-Dist: pyside6; extra == 'dev'
Requires-Dist: pytest; extra == 'dev'
Requires-Dist: pytest-asyncio; extra == 'dev'
Requires-Dist: pytest-cov; extra == 'dev'
Requires-Dist: pytest-mock; extra == 'dev'
Requires-Dist: pytest-order; extra == 'dev'
Requires-Dist: pytest-qt; extra == 'dev'
Requires-Dist: ruff; extra == 'dev'
